aact/__about__.py
aact/__init__.py
aact/py.typed
aact/cli/__init__.py
aact/cli/app.py
aact/cli/launch/__init__.py
aact/cli/launch/launch.py
aact/cli/reader/__init__.py
aact/cli/reader/dataflow_reader.py
aact/messages/__init__.py
aact/messages/base.py
aact/messages/commons.py
aact/messages/registry.py
aact/messages/serialization_utils.py
aact/nodes/__init__.py
aact/nodes/base.py
aact/nodes/listener.py
aact/nodes/performance.py
aact/nodes/print.py
aact/nodes/random.py
aact/nodes/record.py
aact/nodes/registry.py
aact/nodes/speaker.py
aact/nodes/tick.py
aact/nodes/transcriber.py
aact/nodes/tts.py
aact/utils/__init__.py
aact-0.0.10.dist-info/METADATA
aact-0.0.10.dist-info/WHEEL
aact-0.0.10.dist-info/entry_points.txt
aact-0.0.10.dist-info/licenses/LICENSE.md
aact-0.0.10.dist-info/RECORD
